[
  {
    "id": 1,
    "name": "Melbourne Central Car Park",
    "address": "300 Lonsdale St, Melbourne VIC 3000",
    "latitude": -37.8136,
    "longitude": 144.9631,
    "totalSpots": 500,
    "availableSpots": 45,
    "hourlyRate": 8.50,
    "isOpen": true,
    "rating": 4.2,
    "image": "https://images.unsplash.com/photo-1578662996442-48f60103fc96?w=400",
    "description": "Convenient parking in the heart of Melbourne CBD, connected to Melbourne Central shopping centre.",
    "features": ["Covered", "24/7 Access", "Security", "EV Charging"],
    "operatingHours": "24/7"
  },
  {
    "id": 2,
    "name": "Wilson Parking - Collins Street",
    "address": "123 Collins St, Melbourne VIC 3000",
    "latitude": -37.8146,
    "longitude": 144.9632,
    "totalSpots": 300,
    "availableSpots": 12,
    "hourlyRate": 12.00,
    "isOpen": true,
    "rating": 3.8,
    "image": "https://images.unsplash.com/photo-1578662996442-48f60103fc96?w=400",
    "description": "Premium parking location in Melbourne's financial district.",
    "features": ["Covered", "Security", "Valet Service"],
    "operatingHours": "6AM - 10PM"
  },
  {
    "id": 3,
    "name": "Crown Casino Car Park",
    "address": "8 Whiteman St, Southbank VIC 3006",
    "latitude": -37.8226,
    "longitude": 144.9584,
    "totalSpots": 800,
    "availableSpots": 156,
    "hourlyRate": 6.50,
    "isOpen": true,
    "rating": 4.5,
    "image": "https://images.unsplash.com/photo-1578662996442-48f60103fc96?w=400",
    "description": "Large parking facility near Crown Casino and Southbank precinct.",
    "features": ["Covered", "24/7 Access", "Security", "Free for Casino Patrons"],
    "operatingHours": "24/7"
  },
  {
    "id": 4,
    "name": "Federation Square Car Park",
    "address": "Federation Square, Melbourne VIC 3000",
    "latitude": -37.8183,
    "longitude": 144.9691,
    "totalSpots": 200,
    "availableSpots": 0,
    "hourlyRate": 10.00,
    "isOpen": false,
    "rating": 3.9,
    "image": "https://images.unsplash.com/photo-1578662996442-48f60103fc96?w=400",
    "description": "Underground parking at Federation Square, close to major attractions.",
    "features": ["Underground", "Security", "Close to Attractions"],
    "operatingHours": "7AM - 11PM"
  },
  {
    "id": 5,
    "name": "QV Melbourne Car Park",
    "address": "210 Lonsdale St, Melbourne VIC 3000",
    "latitude": -37.8126,
    "longitude": 144.9621,
    "totalSpots": 400,
    "availableSpots": 89,
    "hourlyRate": 9.00,
    "isOpen": true,
    "rating": 4.1,
    "image": "https://images.unsplash.com/photo-1578662996442-48f60103fc96?w=400",
    "description": "Modern parking facility connected to QV shopping centre.",
    "features": ["Covered", "Shopping Centre Access", "Security", "EV Charging"],
    "operatingHours": "6AM - 12AM"
  },
  {
    "id": 6,
    "name": "Emporium Melbourne Car Park",
    "address": "287 Lonsdale St, Melbourne VIC 3000",
    "latitude": -37.8131,
    "longitude": 144.9628,
    "totalSpots": 350,
    "availableSpots": 67,
    "hourlyRate": 11.00,
    "isOpen": true,
    "rating": 4.3,
    "image": "https://images.unsplash.com/photo-1578662996442-48f60103fc96?w=400",
    "description": "Premium parking at Emporium Melbourne luxury shopping centre.",
    "features": ["Covered", "Luxury Shopping", "Security", "Valet Service"],
    "operatingHours": "10AM - 9PM"
  },
  {
    "id": 7,
    "name": "South Wharf Car Park",
    "address": "South Wharf Promenade, Melbourne VIC 3006",
    "latitude": -37.8231,
    "longitude": 144.9589,
    "totalSpots": 250,
    "availableSpots": 34,
    "hourlyRate": 7.50,
    "isOpen": true,
    "rating": 4.0,
    "image": "https://images.unsplash.com/photo-1578662996442-48f60103fc96?w=400",
    "description": "Waterfront parking near South Wharf and Convention Centre.",
    "features": ["Waterfront", "Convention Centre Access", "Security"],
    "operatingHours": "6AM - 10PM"
  }
] 